Workbook

Sheet Sources & Method
A1: 00 | METHODOLOGY & SOURCES
A3: Reference / Topic | B3: Details | C3: Source / Link | D3: Status
A4: Jira baseline | B4: 4 Epics, 17 Stories, 6 Tasks, 117 Subtasks; 110 Done, 3 In Progress, 4 To Do. | C4: Ako_Project.xlsx | D4: Project source
A5: Subtask normalisation | B5: Different decomposition granularity; reference mean 68/15=4.53, approximately 77 equivalent subtasks. | C5: Jira export / project estimation convention | D5: Assumption
A6: Labour estimation | B6: 260 hours allocated by activity; not directly recorded worklogs. | C6: Labour Cost sheet | D6: Planning estimate
A7: Labour rate benchmarks | B7: Rates NZ$75–110/h are budget inputs pending market-source verification. | C7: https://www.h2r.co.nz/h2r-consulting/services/contractors/salary-vs-hourly-rate/contractor-hourly-rate-guide/ | D7: Market reference
A8: Additional rate benchmark | B8: New Zealand salary guide reference; verify comparable hourly contract basis. | C8: https://www.betterworldofwork.io/more-than-money/search-salaries | D8: Market reference
A9: Laptop depreciation | B9: Straight-line 36-month allocation; 0.75 month approximates 3 weeks. | C9: Assumptions sheet | D9: Assumption
A10: Cash vs economic cost | B10: Student labour is valued economically; not treated as paid wages. | C10: Cost Summary and Resources | D10: Method
A11: Contingency | B11: 10% of base economic development cost. | C11: Assumptions sheet | D11: Assumption
A12: Sensitivity | B12: ±10% labour hours or hourly rates; other costs unchanged. | C12: Sensitivity sheet | D12: Scenario

Sheet Assumptions
A1: 01 | MODEL ASSUMPTIONS
A3: Input | B3: Value | C3: Unit / Definition | D3: Basis / Source
A4: Team members | B4: 4 | C4: people | D4: Project team / Jira context
A5: Project duration | B5: 3 | C5: weeks | D5: Project planning assumption
A6: Normalised subtask count | B6: 77.07 | C6: equivalent subtasks | D6: Jira Oct 27 16:30; reference average 4.53
A7: Reference subtasks per story | B7: 4.53 | C7: subtasks/story | D7: Other 15 stories: 68 / 15
A8: Requirements hourly rate | B8: 95 | C8: NZD/hour | D8: H2R Technology — Business Analyst
A9: Management hourly rate | B9: 100 | C9: NZD/hour | D9: H2R Technology — IT Project Manager
A10: Architecture hourly rate | B10: 110 | C10: NZD/hour | D10: H2R Technology — IT Architect
A11: Development hourly rate | B11: 100 | C11: NZD/hour | D11: H2R Technology — Web Developer
A12: Testing hourly rate | B12: 95 | C12: NZD/hour | D12: H2R Technology — Testing / QA
A13: Documentation hourly rate | B13: 75 | C13: NZD/hour | D13: Better World of Work — Technical Writer
A14: Laptop value | B14: 2000 | C14: NZD/device | D14: Planning assumption
A15: Laptop life | B15: 36 | C15: months | D15: Straight-line allocation assumption
... A21: Effort sensitivity | B21: 0.1 | C21: fraction | D21: Scenario assumption

Sheet Jira Workload
A1: 02 | JIRA WORKLOAD BASELINE
A3: Metric | B3: Count | C3: Treatment / Notes | D3: Source
A4: Epics | B4: 4 | C4: Scope grouping only | D4: Jira export
A5: Stories | B5: 17 | C5: Functional scope | D5: Jira export
A6: Tasks | B6: 6 | C6: Planning and project setup | D6: Jira export
A7: Subtasks | B7: 117 | C7: Raw issue count | D7: Jira export
A8: Subtasks Done | B8: 110 | C8: Status at export | D8: Jira export
A9: Subtasks In Progress | B9: 3 | C9: Status at export | D9: Jira export
A10: Subtasks To Do | B10: 4 | C10: Status at export | D10: Jira export
A11: Subtasks linked to Stories | B11: 116 | C11: One subtask not linked to Story | D11: Jira export
A12: Reference Stories | B12: 15 | C12: Excludes exceptionally granular decomposition | D12: Jira normalisation calculation
A13: Reference linked Subtasks | B13: 68 | C13: Reference sample for normalisation | D13: Jira normalisation calculation
A14: Average Subtasks per Story | B14: =ROUND(B13/B12,2) -> 4.53 | C14: Reference sample average | D14: Calculated
A15: Normalised equivalent Subtasks | B15: =ROUND(B13+2*(B13/B12),0) -> 77 | C15: Comparable workload indicator; not hours | D15: Calculated
A16: Recorded Worklogs | B16: 0 | C16: Hours not available; estimates used | D16: Jira export

Sheet Labour Cost
A1: 03 | LABOUR COST ESTIMATE
A3: Activity | B3: Jira / Workstream | C3: Hours | D3: Rate (NZD/h) | E3: Cost (NZD) | F3: Basis
A4: Requirements Analysis | B4: AKO-26 — Requirements and acceptance criteria | C4: 15 | D4: =Assumptions!B8 -> 95 | E4: =C4*D4 -> 1425 | F4: Activity estimate; Jira-linked where applicable
A5: Requirements Analysis | B5: AKO-28 — MVP scope and prioritisation | C5: 10 | D5: =Assumptions!B8 -> 95 | E5: =C5*D5 -> 950 | F5: Activity estimate; Jira-linked where applicable
A6: Requirements Analysis | B6: Stakeholder discussions and requirements refinement | C6: 10 | D6: =Assumptions!B8 -> 95 | E6: =C6*D6 -> 950 | F6: Activity estimate; Jira-linked where applicable
A7: Project Management | B7: AKO-27 — Jira setup and backlog | C7: 10 | D7: =Assumptions!B9 -> 100 | E7: =C7*D7 -> 1000 | F7: Activity estimate; Jira-linked where applicable
A8: Project Management | B8: AKO-29 — Sprint planning and responsibilities | C8: 8 | D8: =Assumptions!B9 -> 100 | E8: =C8*D8 -> 800 | F8: Activity estimate; Jira-linked where applicable
A9: Project Management | B9: Sprint coordination, reviews and meeting records | C9: 12 | D9: =Assumptions!B9 -> 100 | E9: =C9*D9 -> 1200 | F9: Activity estimate; Jira-linked where applicable
A10: Architecture | B10: AKO-30 — Technical architecture | C10: 10 | D10: =Assumptions!B10 -> 110 | E10: =C10*D10 -> 1100 | F10: Activity estimate; Jira-linked where applicable
A11: Architecture | B11: AKO-31 — Repository and development workflow | C11: 5 | D11: =Assumptions!B10 -> 110 | E11: =C11*D11 -> 550 | F11: Activity estimate; Jira-linked where applicable
A12: Architecture | B12: Database, RBAC, UML and UI design | C12: 20 | D12: =Assumptions!B10 -> 110 | E12: =C12*D12 -> 2200 | F12: Activity estimate; Jira-linked where applicable
A13: Development | B13: AKO-8/9 — Authentication and staff accounts | C13: 16 | D13: =Assumptions!B11 -> 100 | E13: =C13*D13 -> 1600 | F13: Activity estimate; Jira-linked where applicable
A14: Development | B14: AKO-10/12/13/22/23 — Learners and attendance | C14: 22 | D14: =Assumptions!B11 -> 100 | E14: =C14*D14 -> 2200 | F14: Activity estimate; Jira-linked where applicable
A15: Development | B15: AKO-11 — Class sessions | C15: 8 | D15: =Assumptions!B11 -> 100 | E15: =C15*D15 -> 800 | F15: Activity estimate; Jira-linked where applicable
A16: Development | B16: AKO-14/16/21 — Lesson library and shared materials | C16: 20 | D16: =Assumptions!B11 -> 100 | E16: =C16*D16 -> 2000 | F16: Activity estimate; Jira-linked where applicable
A17: Development | B17: AKO-15 — Māori content review | C17: 6 | D17: =Assumptions!B11 -> 100 | E17: =C17*D17 -> 600 | F17: Activity estimate; Jira-linked where applicable
A18: Development | B18: AKO-17/18 — Club information and enquiries | C18: 10 | D18: =Assumptions!B11 -> 100 | E18: =C18*D18 -> 1000 | F18: Activity estimate; Jira-linked where applicable
A19: Development | B19: AKO-19/20 — QR attendance functions | C19: 8 | D19: =Assumptions!B11 -> 100 | E19: =C19*D19 -> 800 | F19: Activity estimate; Jira-linked where applicable
A20: Development | B20: AKO-24 — CSV learner import | C20: 6 | D20: =Assumptions!B11 -> 100 | E20: =C20*D20 -> 600 | F20: Activity estimate; Jira-linked where applicable
A21: Development | B21: Cross-feature debugging and adjustments | C21: 4 | D21: =Assumptions!B11 -> 100 | E21: =C21*D21 -> 400 | F21: Activity estimate; Jira-linked where applicable
A22: Testing | B22: Test planning and acceptance test design | C22: 10 | D22: =Assumptions!B12 -> 95 | E22: =C22*D22 -> 950 | F22: Activity estimate; Jira-linked where applicable
A23: Testing | B23: Unit and functional testing | C23: 12 | D23: =Assumptions!B12 -> 95 | E23: =C23*D23 -> 1140 | F23: Activity estimate; Jira-linked where applicable
A24: Testing | B24: Integration and acceptance testing | C24: 9 | D24: =Assumptions!B12 -> 95 | E24: =C24*D24 -> 855 | F24: Activity estimate; Jira-linked where applicable
A25: Testing | B25: Regression testing and defect verification | C25: 4 | D25: =Assumptions!B12 -> 95 | E25: =C25*D25 -> 380 | F25: Activity estimate; Jira-linked where applicable
A26: Documentation | B26: Technical and project documentation | C26: 12 | D26: =Assumptions!B13 -> 75 | E26: =C26*D26 -> 900 | F26: Activity estimate; Jira-linked where applicable
A27: Documentation | B27: Project report preparation | C27: 8 | D27: =Assumptions!B13 -> 75 | E27: =C27*D27 -> 600 | F27: Activity estimate; Jira-linked where applicable
A28: Documentation | B28: Presentation and delivery preparation | C28: 5 | D28: =Assumptions!B13 -> 75 | E28: =C28*D28 -> 375 | F28: Activity estimate; Jira-linked where applicable
A29: TOTAL LABOUR | C29: =SUM(C4:C28) -> 260 | E29: =SUM(E4:E28) -> 25375

Sheet Resources
A1: 04 | ALLOCATED RESOURCES
A3: Resource | B3: Units / People | C3: Unit Cost / Rate | D3: Duration / Basis | E3: Cost (NZD) | F3: Calculation Note
A4: Laptops | B4: 4 | C4: 2000 | D4: 0.75 | E4: =ROUND(B4*C4*D4/Assumptions!B15,2) -> 166.67 | F4: 4 × laptop value ÷ useful life × allocation months
A5: Home office | B5: 4 | C5: 15 | D5: 3 | E5: =B5*C5*D5 -> 180 | F5: 4 members × weekly allocation × 3 weeks
A6: Electricity | B6: 4 | C6: 2 | D6: 3 | E6: =B6*C6*D6 -> 24 | F6: 4 members × weekly allocation × 3 weeks
A7: Internet | B7: 4 | C7: 3 | D7: 3 | E7: =B7*C7*D7 -> 36 | F7: 4 members × weekly allocation × 3 weeks
A8: Cloud hosting | B8: 1 | C8: 0 | D8: 1 | E8: =B8*C8*D8 -> 0 | F8: No paid hosting assumed
A9: TOTAL RESOURCES | E9: =SUM(E4:E8) -> 406.67

Sheet Tools
A1: 05 | SOFTWARE & TOOL COSTS
A3: Tool | B3: Purpose | C3: Cost (NZD) | D3: Licence / Assumption
A4: Jira Free | B4: Agile project management | C4: 0 | D4: Free/open-source or no additional licence cost
A5: GitHub Free | B5: Version control | C5: 0 | D5: Free/open-source or no additional licence cost
A6: Visual Studio Code | B6: Development environment | C6: 0 | D6: Free/open-source or no additional licence cost
A7: Microsoft Teams | B7: Communication | C7: 0 | D7: Free/open-source or no additional licence cost
A8: Next.js | B8: Frontend framework | C8: 0 | D8: Free/open-source or no additional licence cost
A9: React | B9: UI development | C9: 0 | D9: Free/open-source or no additional licence cost
A10: FastAPI | B10: Backend API | C10: 0 | D10: Free/open-source or no additional licence cost
A11: PostgreSQL | B11: Database | C11: 0 | D11: Free/open-source or no additional licence cost
A12: Docker | B12: Containerised development | C12: 0 | D12: Free/open-source or no additional licence cost
A13: Nginx | B13: Web server and routing | C13: 0 | D13: Free/open-source or no additional licence cost
A14: TOTAL TOOLS | C14: =SUM(C4:C13) -> 0

Sheet Cost Summary
A1: 06 | PROJECT COST SUMMARY
A3: Category | B3: Cost (NZD) | C3: Share of Base | D3: Interpretation
A4: Labour | B4: ='Labour Cost'!E29 -> 25375 | C4: =IFERROR(B4/$B$7,0) -> 0.98422639 | D4: Market-valued development effort
A5: Tools | B5: =Tools!C14 -> 0 | C5: =IFERROR(B5/$B$7,0) -> 0 | D5: Free and open-source software
A6: Resources | B6: =Resources!E9 -> 406.67 | C6: =IFERROR(B6/$B$7,0) -> 0.01577361 | D6: Allocated equipment and household resources
A7: BASE DEVELOPMENT COST | B7: =SUM(B4:B6) -> 25781.67 | D7: Economic cost excluding reserve
A8: Contingency (10%) | B8: =ROUND(B7*Assumptions!B20,2) -> 2578.17 | D8: Budget allowance, not incurred expenditure
A9: TOTAL PROJECT BUDGET | B9: =SUM(B7:B8) -> 28359.84 | D9: Base cost plus contingency
A12: Labour activity | B12: Cost (NZD)
A13: Requirements Analysis | B13: =SUMIF('Labour Cost'!A4:A28,A13,'Labour Cost'!E4:E28) -> 3325
A14: Project Management | B14: =SUMIF('Labour Cost'!A4:A28,A14,'Labour Cost'!E4:E28) -> 3000
A15: Architecture | B15: =SUMIF('Labour Cost'!A4:A28,A15,'Labour Cost'!E4:E28) -> 3850
A16: Development | B16: =SUMIF('Labour Cost'!A4:A28,A16,'Labour Cost'!E4:E28) -> 10000
A17: Testing | B17: =SUMIF('Labour Cost'!A4:A28,A17,'Labour Cost'!E4:E28) -> 3325
A18: Documentation | B18: =SUMIF('Labour Cost'!A4:A28,A18,'Labour Cost'!E4:E28) -> 1875

Sheet Sensitivity
A1: 07 | COST SENSITIVITY
A3: Scenario | B3: Labour Multiplier | C3: Labour Cost (NZD) | D3: Base Cost (NZD) | E3: Budget with 10% Reserve
A4: Low (−10%) | B4: =1-Assumptions!B21 -> 0.9 | C4: ='Cost Summary'!B4*B4 -> 22837.5 | D4: =C4+'Cost Summary'!B5+'Cost Summary'!B6 -> 23244.17 | E4: =D4*(1+Assumptions!B20) -> 25568.587
A5: Base | B5: =1 -> 1 | C5: ='Cost Summary'!B4*B5 -> 25375 | D5: =C5+'Cost Summary'!B5+'Cost Summary'!B6 -> 25781.67 | E5: =D5*(1+Assumptions!B20) -> 28359.837
A6: High (+10%) | B6: =1+Assumptions!B21 -> 1.1 | C6: ='Cost Summary'!B4*B6 -> 27912.5 | D6: =C6+'Cost Summary'!B5+'Cost Summary'!B6 -> 28319.17 | E6: =D6*(1+Assumptions!B20) -> 31151.087
A9: The same scenarios apply to proportional hourly-rate changes with hours held constant.
